[
  {
    "title": "Bachelor Degree of Computer Science (Hons)",
    "institution": "University Of StaffordShire, UK",
    "institutionUrl": "#",
    "desc": "2nd Upper Division Honours in Computer Science.",
    "year": "2023 - 2024"
  },
  {
    "title": "HND In Artificial Intelligence",
    "institution": "Pearson, UK",
    "institutionUrl": "#",
    "desc": "At American College of Higher Education, I completed my HND in Artificial Intelligence.",
    "year": "2019 - 2023"
  },
  {
    "title": "Agriculture Sales Technician Programme",
    "institution": "Department Of Agriculture, Sri Lanka.",
    "institutionUrl": "#",
    "desc": "Completed a diploma course on Agriculture Sales Technician Programme conducted by the Department Of Agriculture, Sri Lanka.",
    "year": "2016 - 2017"
  },
  {
    "title": "DIPLOMA IN CAD AND BS",
    "institution": "Pearson, UK",
    "institutionUrl": "#",
    "desc": "Completed a diploma course on Computer Aided Design and Building Services Engineering.And Batch Topper of 2015.",
    "year": "2014 - 2015"
  }
  ,
  {
    "title": "GCE Advanced Level",
    "institution": "Galgamuwa Central College",
    "institutionUrl": "#",
    "desc": "Commerce Stream",
    "year": "2011 - 2013"
  }
]
